jinil_test/test1.py
jinil_test/test2.py
jinil_test-0.0.0.2.dist-info/METADATA
jinil_test-0.0.0.2.dist-info/WHEEL
jinil_test-0.0.0.2.dist-info/top_level.txt
jinil_test-0.0.0.2.dist-info/RECORD
