Metadata-Version: 2.1
Name: jinil-test
Version: 0.0.0.2
Summary: My First Test Package
Home-page: https://naver.com
Author: Jinil
Author-email: climson@hanmail.net
License: MIT
Requires-Python: >=3
